LICENSE
MANIFEST.in
README
run
setup.py
bin/cvu
cvu/__init__.py
cvu/circle_plot.py
cvu/color_axis.py
cvu/color_legend.py
cvu/color_map.py
cvu/controller.py
cvu/custom_file_editor.py
cvu/dataset.py
cvu/dataview.py
cvu/dialogs.py
cvu/directory_dialog.py
cvu/graph.py
cvu/gui.py
cvu/main.py
cvu/monolithic_cvu.py
cvu/mpleditor.py
cvu/options_struct.py
cvu/parsing_utils.py
cvu/preprocessing.py
cvu/shell_utils.py
cvu/tractography.py
cvu/utils.py
cvu/viewport.py
cvu/volume.py
cvu.egg-info/PKG-INFO
cvu.egg-info/SOURCES.txt
cvu.egg-info/dependency_links.txt
cvu.egg-info/requires.txt
cvu.egg-info/top_level.txt
cvu/cmap_images/README.txt
cvu/cmap_images/__init__.py
cvu/cmap_images/__init__.pyc
cvu/cmap_images/accent.gif
cvu/cmap_images/autumn.gif
cvu/cmap_images/autumn.png
cvu/cmap_images/binary.gif
cvu/cmap_images/black-white.gif
cvu/cmap_images/blue-red.gif
cvu/cmap_images/blues.gif
cvu/cmap_images/bone.gif
cvu/cmap_images/brbg.gif
cvu/cmap_images/bugn.gif
cvu/cmap_images/bupu.gif
cvu/cmap_images/cool.gif
cvu/cmap_images/copper.gif
cvu/cmap_images/custom_heat.gif
cvu/cmap_images/custom_heat_1t.gif
cvu/cmap_images/dark2.gif
cvu/cmap_images/file.gif
cvu/cmap_images/flag.gif
cvu/cmap_images/gist_earth.gif
cvu/cmap_images/gist_gray.gif
cvu/cmap_images/gist_heat.gif
cvu/cmap_images/gist_ncar.gif
cvu/cmap_images/gist_rainbow.gif
cvu/cmap_images/gist_stern.gif
cvu/cmap_images/gist_yarg.gif
cvu/cmap_images/gnbu.gif
cvu/cmap_images/gray.gif
cvu/cmap_images/greens.gif
cvu/cmap_images/greys.gif
cvu/cmap_images/hot.gif
cvu/cmap_images/hsv.gif
cvu/cmap_images/jet.gif
cvu/cmap_images/oranges.gif
cvu/cmap_images/orrd.gif
cvu/cmap_images/paired.gif
cvu/cmap_images/pastel1.gif
cvu/cmap_images/pastel2.gif
cvu/cmap_images/pink.gif
cvu/cmap_images/piyg.gif
cvu/cmap_images/prgn.gif
cvu/cmap_images/prism.gif
cvu/cmap_images/pubu.gif
cvu/cmap_images/pubugn.gif
cvu/cmap_images/puor.gif
cvu/cmap_images/purd.gif
cvu/cmap_images/purples.gif
cvu/cmap_images/pylab_luts.pkl
cvu/cmap_images/rdbu.gif
cvu/cmap_images/rdgy.gif
cvu/cmap_images/rdpu.gif
cvu/cmap_images/rdylbu.gif
cvu/cmap_images/rdylgn.gif
cvu/cmap_images/reds.gif
