Metadata-Version: 1.1
Name: cvu
Version: 0.5.2
Summary: A visualizer for human brain networks
Home-page: https://github.com/aestrivex/cvu
Author: Roan LaPlante
Author-email: rlaplant@nmr.mgh.harvard.edu
License: Visuddhimagga Sutta; GPLv3+
Platform: any
Classifier: Development Status :: 4 - Beta
Classifier: Environment :: X11 Applications
Classifier: Intended Audience :: Science/Research
Classifier: License :: OSI Approved :: GNU General Public License v3 or later (GPLv3+)
Classifier: Natural Language :: English
Classifier: Programming Language :: Python :: 2.7
Classifier: Topic :: Scientific/Engineering :: Visualization
